asqlcell/__init__.py
asqlcell/_frontend.py
asqlcell/_version.py
asqlcell/chart.py
asqlcell/jinjasql.py
asqlcell/magic.py
asqlcell/utils.py
asqlcell/widget.py
asqlcell/labextension/package.json
asqlcell/labextension/static/103.6353a1079a6cd5f0e6a5.js
asqlcell/labextension/static/118.202410f8fcc13a6a7de8.js
asqlcell/labextension/static/154.d16c2a81345f53f7a1d1.js
asqlcell/labextension/static/154.d16c2a81345f53f7a1d1.js.LICENSE.txt
asqlcell/labextension/static/243.fec870a3206af0837731.js
asqlcell/labextension/static/444.19ab6fa22728382fffa6.js
asqlcell/labextension/static/456.2d30a468feebb1131c3e.js
asqlcell/labextension/static/480.b5b508ef6497b1530a25.js
asqlcell/labextension/static/504.16fde067abbcd1631d3a.js
asqlcell/labextension/static/568.156765388c1b45f13275.js
asqlcell/labextension/static/594.283402ea8e1cbd305f37.js
asqlcell/labextension/static/594.283402ea8e1cbd305f37.js.LICENSE.txt
asqlcell/labextension/static/641.682b0850093aaa73b27f.js
asqlcell/labextension/static/665.69cf718f2e81e1466bed.js
asqlcell/labextension/static/725.b86e7e512e5ddfabbafd.js
asqlcell/labextension/static/74.b3455c1e4f213022f3a4.js
asqlcell/labextension/static/823.5b6b70ecac956db20d91.js
asqlcell/labextension/static/839.0f28558516c809d33355.js
asqlcell/labextension/static/877.12fdbe1c7abf30c963c5.js
asqlcell/labextension/static/901.41c541831fccac99f536.js
asqlcell/labextension/static/990.ffdf4b48e6e885a7111f.js
asqlcell/labextension/static/remoteEntry.0ccd790537f84d5716f8.js
asqlcell/labextension/static/style.js
asqlcell/labextension/static/third-party-licenses.json
asqlcell/nbextension/extension.js
asqlcell/nbextension/index.js
asqlcell/nbextension/index.js.LICENSE.txt
asqlcell/nbextension/index.js.map
asqlcell/tests/__init__.py
asqlcell/tests/conftest.py
asqlcell/tests/test_duckdb.py
asqlcell/tests/test_extension.py
asqlcell/tests/test_magic.py
asqlcell/tests/test_mysql.py
asqlcell/tests/test_postgresql.py
asqlcell/tests/test_sqlite.py
asqlcell/tests/test_widget.py
asqlcell-0.3.1.0.dist-info/METADATA
asqlcell-0.3.1.0.dist-info/WHEEL
asqlcell-0.3.1.0.dist-info/top_level.txt
asqlcell-0.3.1.0.dist-info/RECORD
