Metadata-Version: 2.1
Name: asqlcell
Version: 0.3.1.0
Summary: Analytical sql cell for Jupyter
Home-page: https://github.com/datarho/asqlcell
Author: qizh
Author-email: qizh@datarho.tech
License: BSD
Keywords: Jupyter,Widgets,IPython
Platform: Linux
Platform: Mac OS X
Platform: Windows
Classifier: Intended Audience :: Developers
Classifier: Intended Audience :: Science/Research
Classifier: License :: OSI Approved :: BSD License
Classifier: Programming Language :: Python
Classifier: Programming Language :: Python :: 3
Classifier: Programming Language :: Python :: 3.4
Classifier: Programming Language :: Python :: 3.5
Classifier: Programming Language :: Python :: 3.6
Classifier: Programming Language :: Python :: 3.7
Classifier: Programming Language :: Python :: 3.8
Classifier: Framework :: Jupyter
Requires-Python: >=3.8
Requires-Dist: altair ==5.2.0
Requires-Dist: vegafusion ==1.6.1
Requires-Dist: vl-convert-python ==1.2.1
Requires-Dist: vegafusion-python-embed ==1.6.1
Requires-Dist: duckdb ==1.0.0
Requires-Dist: duckdb-engine ==0.13.0
Requires-Dist: pandas ==2.0.3
Requires-Dist: sqlalchemy ==2.0.19
Requires-Dist: fastparquet >=2023.4.0
Requires-Dist: ipywidgets >=8.0.0
Requires-Dist: jinja2 >=3.1.2
Requires-Dist: StrEnum >=0.4.15
Requires-Dist: sqlparse >=0.4.3
Requires-Dist: openpyxl >=3.1.2
Provides-Extra: docs
Requires-Dist: jupyter-sphinx ; extra == 'docs'
Requires-Dist: nbsphinx ; extra == 'docs'
Requires-Dist: nbsphinx-link ; extra == 'docs'
Requires-Dist: pytest-check-links ; extra == 'docs'
Requires-Dist: pypandoc ; extra == 'docs'
Requires-Dist: recommonmark ; extra == 'docs'
Requires-Dist: sphinx >=1.5 ; extra == 'docs'
Requires-Dist: sphinx-rtd-theme ; extra == 'docs'
Provides-Extra: examples
Provides-Extra: test
Requires-Dist: pytest >=4.6 ; extra == 'test'
Requires-Dist: pytest-cov ; extra == 'test'
Requires-Dist: nbval ; extra == 'test'
